{"lst_buffer_random":[0.3881754185291033,0.09784844067792275,0.591049066332163,0.44200420351453773],"colors":{"r":0,"g":-5,"b":-4,"a":-2},"parameter":{"2928":{"name":"DEPTH_RANGE","type":"decimal","isArray":true,"fake_value":0.2782258458959499},"3379":{"name":"MAX_TEXTURE_SIZE","type":"shift","max":1,"fake_value":0},"3386":{"name":"MAX_VIEWPORT_DIMS","type":"shift","max":1,"isArray":true,"fake_value":1},"32883":{"name":"MAX_3D_TEXTURE_SIZE","type":"shift","max":1,"fake_value":0},"33000":{"name":"MAX_ELEMENTS_VERTICES","type":"-","max":3,"factor":50,"fake_value":150},"33001":{"name":"MAX_ELEMENTS_INDICES","type":"-","max":3,"factor":50,"fake_value":100},"33901":{"name":"ALIASED_POINT_SIZE_RANGE","type":"decimal","isArray":true,"fake_value":0.40122724848541513},"33902":{"name":"ALIASED_LINE_WIDTH_RANGE","type":"decimal","isArray":true,"fake_value":0.958424575204571},"34024":{"name":"MAX_RENDERBUFFER_SIZE","type":"shift","max":1,"fake_value":1},"34045":{"name":"MAX_TEXTURE_LOD_BIAS","type":"-","max":1,"factor":1,"fake_value":1},"34076":{"name":"MAX_CUBE_MAP_TEXTURE_SIZE","type":"shift","max":1,"fake_value":0},"34921":{"name":"MAX_VERTEX_ATTRIBS","type":"shift","max":1,"fake_value":1},"34930":{"name":"MAX_TEXTURE_IMAGE_UNITS","type":"shift","max":1,"fake_value":0},"35071":{"name":"MAX_ARRAY_TEXTURE_LAYERS","type":"shift","max":1,"fake_value":0},"35371":{"name":"MAX_VERTEX_UNIFORM_BLOCKS","type":"-","max":1,"factor":1,"fake_value":1},"35373":{"name":"MAX_FRAGMENT_UNIFORM_BLOCKS","type":"-","max":1,"factor":1,"fake_value":1},"35374":{"name":"MAX_COMBINED_UNIFORM_BLOCKS","type":"-","max":3,"factor":1,"fake_value":1},"35375":{"name":"MAX_UNIFORM_BUFFER_BINDINGS","type":"-","max":3,"factor":1,"fake_value":2},"35376":{"name":"MAX_UNIFORM_BLOCK_SIZE","type":"shift","max":1,"fake_value":0},"35377":{"name":"MAX_COMBINED_VERTEX_UNIFORM_COMPONENTS","type":"-","max":7,"factor":10,"fake_value":70},"35379":{"name":"MAX_COMBINED_FRAGMENT_UNIFORM_COMPONENTS","type":"-","max":7,"factor":10,"fake_value":10},"35657":{"name":"MAX_FRAGMENT_UNIFORM_COMPONENTS","type":"shift","max":1,"fake_value":0},"35658":{"name":"MAX_VERTEX_UNIFORM_COMPONENTS","type":"shift","max":1,"fake_value":1},"35659":{"name":"MAX_VARYING_COMPONENTS","type":"shift","max":1,"fake_value":0},"35660":{"name":"MAX_VERTEX_TEXTURE_IMAGE_UNITS","type":"shift","max":1,"fake_value":1},"35661":{"name":"MAX_COMBINED_TEXTURE_IMAGE_UNITS","type":"-","max":1,"factor":2,"fake_value":2},"35968":{"name":"MAX_TRANSFORM_FEEDBACK_SEPARATE_COMPONENTS","type":"shift","max":1,"fake_value":1},"35978":{"name":"MAX_TRANSFORM_FEEDBACK_INTERLEAVED_COMPONENTS","type":"shift","max":1,"fake_value":0},"36203":{"name":"MAX_ELEMENT_INDEX","type":"-","max":15,"factor":1,"fake_value":14},"36347":{"name":"MAX_VERTEX_UNIFORM_VECTORS","type":"shift","max":1,"fake_value":1},"36348":{"name":"MAX_VARYING_VECTORS","type":"shift","max":1,"fake_value":0},"36349":{"name":"MAX_FRAGMENT_UNIFORM_VECTORS","type":"shift","max":1,"fake_value":1},"37154":{"name":"MAX_VERTEX_OUTPUT_COMPONENTS","type":"shift","max":1,"fake_value":0},"37157":{"name":"MAX_FRAGMENT_INPUT_COMPONENTS","type":"shift","max":1,"fake_value":0}}}